setup.py
txamqp_helpers/__init__.py
txamqp_helpers/amqp.py
txamqp_helpers.egg-info/PKG-INFO
txamqp_helpers.egg-info/SOURCES.txt
txamqp_helpers.egg-info/dependency_links.txt
txamqp_helpers.egg-info/not-zip-safe
txamqp_helpers.egg-info/requires.txt
txamqp_helpers.egg-info/top_level.txt