Metadata-Version: 1.0
Name: txamqp-helpers
Version: 0.5
Summary: txAMQP Helpers
Home-page: https://github.com/williamsjj/txamqp-helpers
Author: Jason Williams/Dan Siemon
Author-email: jasonjwwilliams@gmail.com
License: Apache 2.0
Download-URL: https://github.com/williamsjj/txamqp-helpers/zipball/v0.5
Platform: UNKNOWN
